README.md
setup.py
panamap/__init__.py
panamap/panamap.py
panamap/panamap.version
panamap/tools.py
panamap.egg-info/PKG-INFO
panamap.egg-info/SOURCES.txt
panamap.egg-info/dependency_links.txt
panamap.egg-info/requires.txt
panamap.egg-info/top_level.txt