Metadata-Version: 2.1
Name: panamap
Version: 1.2.1
Summary: Python object mapper
Home-page: https://github.com/kirillsulim/panamap
Author: Kirill Sulim
Author-email: kirillsulim@gmail.com
License: MIT
Keywords: object mapper
Platform: UNKNOWN
Classifier: Development Status :: 4 - Beta
Classifier: License :: OSI Approved :: MIT License
Classifier: Programming Language :: Python :: 3.7
Classifier: Programming Language :: Python :: 3.8
